gradientai/__init__.py
gradientai/__init__.pyi
gradientai/_base_model.py
gradientai/_embeddings_model.py
gradientai/_gradient.py
gradientai/_model.py
gradientai/_model_adapter.py
gradientai/_rag.py
gradientai/_types.py
gradientai/helpers/asyncio_threads.py
gradientai/helpers/env_manager.py
gradientai/openapi/__init__.py
gradientai/openapi/client/__init__.py
gradientai/openapi/client/api/__init__.py
gradientai/openapi/client/api/blocks_api.py
gradientai/openapi/client/api/embeddings_api.py
gradientai/openapi/client/api/files_api.py
gradientai/openapi/client/api/models_api.py
gradientai/openapi/client/api/rag_api.py
gradientai/openapi/client/api_client.py
gradientai/openapi/client/api_response.py
gradientai/openapi/client/configuration.py
gradientai/openapi/client/docs/AddFilesToRagCollectionBodyParams.md
gradientai/openapi/client/docs/AddFilesToRagCollectionError.md
gradientai/openapi/client/docs/AnalyzeSentimentBodyParams.md
gradientai/openapi/client/docs/AnalyzeSentimentBodyParamsExamplesInner.md
gradientai/openapi/client/docs/AnalyzeSentimentError.md
gradientai/openapi/client/docs/AnalyzeSentimentSuccess.md
gradientai/openapi/client/docs/BaseModel.md
gradientai/openapi/client/docs/BlocksApi.md
gradientai/openapi/client/docs/CompleteModelBodyParams.md
gradientai/openapi/client/docs/CompleteModelBodyParamsGuidance.md
gradientai/openapi/client/docs/CompleteModelBodyParamsRag.md
gradientai/openapi/client/docs/CompleteModelError.md
gradientai/openapi/client/docs/CompleteModelErrorOneOf.md
gradientai/openapi/client/docs/CompleteModelErrorOneOf1.md
gradientai/openapi/client/docs/CompleteModelErrorOneOf10.md
gradientai/openapi/client/docs/CompleteModelErrorOneOf1Payload.md
gradientai/openapi/client/docs/CompleteModelErrorOneOf2.md
gradientai/openapi/client/docs/CompleteModelErrorOneOf3.md
gradientai/openapi/client/docs/CompleteModelErrorOneOf4.md
gradientai/openapi/client/docs/CompleteModelErrorOneOf5.md
gradientai/openapi/client/docs/CompleteModelErrorOneOf6.md
gradientai-1.13.0.dist-info/METADATA
gradientai-1.13.0.dist-info/WHEEL
gradientai-1.13.0.dist-info/RECORD
